{"items":[{"id":2,"code":"FUNC","title":"Functional Spanish 1","description":"Functional Spanish 1","heroImageUrl":null,"isActive":1,"stepCount":1,"priceInCents":null,"stripePriceId":null,"levels":[],"availableCohorts":1,"nextCohortStartDate":null},{"id":3,"code":"TEST","title":"tests course","description":"abc","heroImageUrl":null,"isActive":1,"stepCount":0,"priceInCents":null,"stripePriceId":null,"levels":[],"availableCohorts":0,"nextCohortStartDate":null},{"id":4,"code":"A","title":"Course A","description":"Course A description","heroImageUrl":null,"isActive":1,"stepCount":1,"priceInCents":9900,"stripePriceId":"price_1SOQ2YHrimnzYL8UTL94cpye","levels":[{"id":1,"code":"A1","name":"Beginner A1"},{"id":2,"code":"A2","name":"Elementary A2"}],"availableCohorts":2,"nextCohortStartDate":null},{"id":5,"code":"AWS","title":"Awesome Course","description":"This course is awesome.","heroImageUrl":"http://localhost:8080/wp-content/uploads/2025/11/565633059_838533358711949_946630111899637072_n.jpg","isActive":1,"stepCount":2,"priceInCents":6700,"stripePriceId":"price_1SUz6EHrimnzYL8Utcn1n3xu","levels":[{"id":3,"code":"B1","name":"Intermediate B1"},{"id":4,"code":"B2","name":"Upper Intermediate B2"}],"availableCohorts":1,"nextCohortStartDate":"2025-12-02T14:00:00.000Z"}],"total":4,"page":1,"pageSize":6}